great_plugin_hlin/__init__.py
great_plugin_hlin/plugin.py
great_plugin_hlin-0.3.0.dist-info/METADATA
great_plugin_hlin-0.3.0.dist-info/WHEEL
great_plugin_hlin-0.3.0.dist-info/entry_points.txt
great_plugin_hlin-0.3.0.dist-info/RECORD
